cmat2aset310/__init__.py
cmat2aset310/cmat2aset.pyc
cmat2aset310/cmat2tset.py
cmat2aset310/gen_aset.py
cmat2aset310/gen_pset.py
cmat2aset310/get_angle.py
cmat2aset310/interpolate_pset.py
LICENSE
cmat2aset310-0.1.0.dist-info/LICENSE
cmat2aset310-0.1.0.dist-info/METADATA
cmat2aset310-0.1.0.dist-info/WHEEL
cmat2aset310-0.1.0.dist-info/RECORD
