Metadata-Version: 2.1
Name: cmat2aset310
Version: 0.1.0
Summary: correlation matrix to align set for python 3.10
Home-page: https://github.com/ffreemt/cmat2aset310
License: MIT
Author: ffreemt
Requires-Python: >=3.10,<3.11
Classifier: License :: OSI Approved :: MIT License
Classifier: Programming Language :: Python :: 3
Classifier: Programming Language :: Python :: 3.10
Requires-Dist: icecream (>=2.1.1,<3.0.0)
Requires-Dist: install (>=1.3.5,<2.0.0)
Requires-Dist: logzero (>=1.7.0,<2.0.0)
Requires-Dist: numpy (>=1.22.3,<2.0.0)
Requires-Dist: pandas (>=1.4.1,<2.0.0)
Requires-Dist: scikit-learn (>=1.2.0,<2.0.0)
Requires-Dist: set-loglevel (>=0.1.2,<0.2.0)
Project-URL: Repository, https://github.com/ffreemt/cmat2aset310
